hubcap/__init__.py
hubcap/base.py
hubcap/constants.py
hubcap/repo_slurp.py
hubcap/tools.py
hubcap/util.py
hubcap/data/dflt_repo_collections_key_props.json
hubcap/examples/__init__.py
hubcap/examples/diagnose_repositories.py
hubcap/examples/get_discussions.py
hubcap/examples/get_wikis.py
hubcap/scrap/__init__.py
hubcap/scrap/direct_github_api.py
hubcap-0.1.20.dist-info/METADATA
hubcap-0.1.20.dist-info/WHEEL
hubcap-0.1.20.dist-info/licenses/LICENSE
hubcap-0.1.20.dist-info/RECORD
