Metadata-Version: 2.4
Name: hubcap
Version: 0.1.20
Summary: A dol (i.e. dict-like) interface to github
Project-URL: Homepage, https://github.com/thorwhalen/hubcap
Author: Thor Whalen
License: Apache-2.0
License-File: LICENSE
Keywords: github
Requires-Python: >=3.10
Requires-Dist: config2py
Requires-Dist: dol
Requires-Dist: lkj
Requires-Dist: pygithub
Requires-Dist: requests
